<Properties StartupConfiguration="{9ED4465F-B681-1EF5-B62C-C6C1D35A1172}|">
  <MonoDevelop.Ide.Workbench>
    <Files>
      <File FileName="Assets/Scripts/Player.cs" Line="38" Column="6" />
      <File FileName="Assets/Scripts/CameraFollow.cs" Line="18" Column="98" />
      <File FileName="Assets/Scripts/GenerateLevelBlocks.cs" Line="29" Column="42" />
    </Files>
    <Pads>
      <Pad Id="ProjectPad">
        <State name="__root__">
          <Node name="Platformer001" expanded="True">
            <Node name="Assets" expanded="True">
              <Node name="Scripts" expanded="True">
                <Node name="GenerateLevelBlocks.cs" selected="True" />
              </Node>
            </Node>
          </Node>
        </State>
      </Pad>
    </Pads>
  </MonoDevelop.Ide.Workbench>
  <MonoDevelop.Ide.DebuggingService.PinnedWatches />
  <MonoDevelop.Ide.Workspace ActiveConfiguration="Debug" />
  <MonoDevelop.Ide.ItemProperties.Assembly-CSharp PreferredExecutionTarget="df4a0fa6-9607-45c5-b384-c3a190d16b72" />
  <MonoDevelop.Ide.DebuggingService.Breakpoints>
    <BreakpointStore />
  </MonoDevelop.Ide.DebuggingService.Breakpoints>
  <MultiItemStartupConfigurations />
</Properties>